pytest_fixture_ref/__init__.py
pytest_fixture_ref-0.0.4.dist-info/WHEEL
pytest_fixture_ref-0.0.4.dist-info/METADATA
pytest_fixture_ref-0.0.4.dist-info/RECORD
